lushlayers/__init__.py
lushlayers/__main__.py
lushlayers/api.py
lushlayers/config.py
lushlayers/karabiner.py
lushlayers/keys.py
lushlayers/parser.py
lushlayers-0.4.0.dist-info/LICENSE
lushlayers-0.4.0.dist-info/METADATA
lushlayers-0.4.0.dist-info/WHEEL
lushlayers-0.4.0.dist-info/entry_points.txt
lushlayers-0.4.0.dist-info/RECORD
