Metadata-Version: 2.1
Name: lushlayers
Version: 0.4.0
Summary: Turn your keyboard into hot lasagna.
Home-page: https://github.com/mdwint/lushlayers
License: MIT
Keywords: keyboard,hotkeys,karabiner-elements
Author: Matteo De Wint
Author-email: matteo@mailfence.com
Requires-Python: >=3.11,<4.0
Classifier: License :: OSI Approved :: MIT License
Classifier: Programming Language :: Python :: 3
Classifier: Programming Language :: Python :: 3.11
Requires-Dist: pydantic (>=2.1.1,<3.0.0)
Project-URL: Repository, https://github.com/mdwint/lushlayers
